<?xml version="1.0" encoding="UTF-8"?>
<objects serializationModel="Studio.01.10.00">
    <object class="Event" id="{a0e33e5a-2c35-4772-a0bb-717c7ba405b8}">
        <property name="name">
            <value>Atmo Tundra</value>
        </property>
        <property name="outputFormat">
            <value>2</value>
        </property>
        <relationship name="folder">
            <destination>{24ea1ec7-b774-467a-8622-dd51ca49d093}</destination>
        </relationship>
        <relationship name="mixer">
            <destination>{f3dbb26a-c984-48a7-a8d9-09378b38a5d6}</destination>
        </relationship>
        <relationship name="masterTrack">
            <destination>{503d924c-23da-4b97-9928-79947ff69343}</destination>
        </relationship>
        <relationship name="mixerInput">
            <destination>{79979731-9ef0-4420-a424-7f9235d9cd2c}</destination>
        </relationship>
        <relationship name="automatableProperties">
            <destination>{5ac9b951-c916-4d0c-91cb-8607e494fd1e}</destination>
        </relationship>
        <relationship name="markerTracks">
            <destination>{ba969300-dd5a-46e4-aa32-4340c05d744c}</destination>
        </relationship>
        <relationship name="groupTracks">
            <destination>{83aadb02-2e1a-4cb2-9ca4-05448a6c8b2f}</destination>
            <destination>{d54800df-0fa6-43cb-821d-9fef628d026f}</destination>
            <destination>{2d0f68a8-c9a6-472b-9f77-5d9fe46def74}</destination>
        </relationship>
        <relationship name="timeline">
            <destination>{89b939f2-3742-49a3-a9ae-24751a173f98}</destination>
        </relationship>
        <relationship name="banks">
            <destination>{1ef2a68a-a823-4315-9cd1-94f9d1c29844}</destination>
        </relationship>
    </object>
    <object class="EventMixer" id="{f3dbb26a-c984-48a7-a8d9-09378b38a5d6}">
        <relationship name="masterBus">
            <destination>{28b4bec2-afcb-4302-b2da-a00dad053f3f}</destination>
        </relationship>
    </object>
    <object class="MasterTrack" id="{503d924c-23da-4b97-9928-79947ff69343}">
        <relationship name="mixerGroup">
            <destination>{28b4bec2-afcb-4302-b2da-a00dad053f3f}</destination>
        </relationship>
    </object>
    <object class="MixerInput" id="{79979731-9ef0-4420-a424-7f9235d9cd2c}">
        <relationship name="effectChain">
            <destination>{87027fc8-2f5a-42ac-802c-9b284f4d9c1d}</destination>
        </relationship>
        <relationship name="panner">
            <destination>{c54528b6-de55-4019-b2ec-2ba331f4e184}</destination>
        </relationship>
        <relationship name="output">
            <destination>{ff151beb-9706-409f-a74d-329009ab1cb2}</destination>
        </relationship>
    </object>
    <object class="EventAutomatableProperties" id="{5ac9b951-c916-4d0c-91cb-8607e494fd1e}"/>
    <object class="MarkerTrack" id="{ba969300-dd5a-46e4-aa32-4340c05d744c}"/>
    <object class="GroupTrack" id="{83aadb02-2e1a-4cb2-9ca4-05448a6c8b2f}">
        <relationship name="modules">
            <destination>{90e4e204-7423-49e8-ae96-cf10405ea3a8}</destination>
        </relationship>
        <relationship name="mixerGroup">
            <destination>{9df51efc-0c66-473f-b142-59df97d250d9}</destination>
        </relationship>
    </object>
    <object class="GroupTrack" id="{d54800df-0fa6-43cb-821d-9fef628d026f}">
        <relationship name="mixerGroup">
            <destination>{3fa69dae-671d-4578-b11c-9b78c348ebf5}</destination>
        </relationship>
    </object>
    <object class="GroupTrack" id="{2d0f68a8-c9a6-472b-9f77-5d9fe46def74}">
        <relationship name="modules">
            <destination>{655c7e04-594b-4528-8f0d-d7ecada9cbd7}</destination>
        </relationship>
        <relationship name="mixerGroup">
            <destination>{a9f768d0-209e-467e-9159-b087a5373507}</destination>
        </relationship>
    </object>
    <object class="Timeline" id="{89b939f2-3742-49a3-a9ae-24751a173f98}">
        <relationship name="modules">
            <destination>{90e4e204-7423-49e8-ae96-cf10405ea3a8}</destination>
            <destination>{655c7e04-594b-4528-8f0d-d7ecada9cbd7}</destination>
        </relationship>
        <relationship name="markers">
            <destination>{1a219a51-ab07-4e05-984b-a02298d85b37}</destination>
        </relationship>
    </object>
    <object class="EventMixerMaster" id="{28b4bec2-afcb-4302-b2da-a00dad053f3f}">
        <relationship name="effectChain">
            <destination>{9248f8b9-2d89-4bd0-a0e0-4768da0dbd3e}</destination>
        </relationship>
        <relationship name="panner">
            <destination>{5b5fc3e6-0aef-4f78-b465-fbec0dfb90ba}</destination>
        </relationship>
        <relationship name="mixer">
            <destination>{f3dbb26a-c984-48a7-a8d9-09378b38a5d6}</destination>
        </relationship>
    </object>
    <object class="MixerBusEffectChain" id="{87027fc8-2f5a-42ac-802c-9b284f4d9c1d}">
        <relationship name="effects">
            <destination>{1068a2bf-0aac-4543-9703-fb0af130f905}</destination>
        </relationship>
    </object>
    <object class="MixerBusPanner" id="{c54528b6-de55-4019-b2ec-2ba331f4e184}"/>
    <object class="SingleSound" id="{90e4e204-7423-49e8-ae96-cf10405ea3a8}">
        <property name="length">
            <value>39.400231189032226</value>
        </property>
        <relationship name="fadeInCurve">
            <destination>{3bb87964-4343-4950-95f3-31ccfe251980}</destination>
        </relationship>
        <relationship name="audioFile">
            <destination>{d6f5269c-0781-41a5-be6f-8cfdeb782dee}</destination>
        </relationship>
    </object>
    <object class="EventMixerGroup" id="{9df51efc-0c66-473f-b142-59df97d250d9}">
        <property name="volume">
            <value>-18</value>
        </property>
        <property name="name">
            <value>Sand</value>
        </property>
        <relationship name="effectChain">
            <destination>{4d6e0110-4b63-4ef2-abad-6acacf5e14de}</destination>
        </relationship>
        <relationship name="panner">
            <destination>{6783ff2a-12ee-4177-846b-4cf5a04a132b}</destination>
        </relationship>
        <relationship name="output">
            <destination>{28b4bec2-afcb-4302-b2da-a00dad053f3f}</destination>
        </relationship>
    </object>
    <object class="EventMixerGroup" id="{3fa69dae-671d-4578-b11c-9b78c348ebf5}">
        <property name="name">
            <value>Wind</value>
        </property>
        <relationship name="effectChain">
            <destination>{3804ea53-b0d8-4269-8f5b-53eb305e14f3}</destination>
        </relationship>
        <relationship name="panner">
            <destination>{30ffef6e-118d-4d28-afca-94d3ecbb1d33}</destination>
        </relationship>
        <relationship name="output">
            <destination>{28b4bec2-afcb-4302-b2da-a00dad053f3f}</destination>
        </relationship>
    </object>
    <object class="SingleSound" id="{655c7e04-594b-4528-8f0d-d7ecada9cbd7}">
        <property name="length">
            <value>39.400231189032226</value>
        </property>
        <property name="timelockedOffset">
            <value>4.3164620676100611</value>
        </property>
        <relationship name="fadeInCurve">
            <destination>{c7ea6da9-ab3c-463b-8ac6-58139b93c1ba}</destination>
        </relationship>
        <relationship name="audioFile">
            <destination>{28927e85-0e67-4dad-bd6b-65853c15273b}</destination>
        </relationship>
    </object>
    <object class="EventMixerGroup" id="{a9f768d0-209e-467e-9159-b087a5373507}">
        <property name="name">
            <value>Audio 1</value>
        </property>
        <relationship name="effectChain">
            <destination>{94faf1a6-c530-437f-83e5-f9714b7c647c}</destination>
        </relationship>
        <relationship name="panner">
            <destination>{00ddd211-69ac-4dd0-aca9-935acb94e80c}</destination>
        </relationship>
        <relationship name="output">
            <destination>{28b4bec2-afcb-4302-b2da-a00dad053f3f}</destination>
        </relationship>
    </object>
    <object class="LoopRegion" id="{1a219a51-ab07-4e05-984b-a02298d85b37}">
        <property name="position">
            <value>7.5905162047955983</value>
        </property>
        <property name="length">
            <value>27.05061379716981</value>
        </property>
        <relationship name="timeline">
            <destination>{89b939f2-3742-49a3-a9ae-24751a173f98}</destination>
        </relationship>
        <relationship name="markerTrack">
            <destination>{ba969300-dd5a-46e4-aa32-4340c05d744c}</destination>
        </relationship>
    </object>
    <object class="MixerBusEffectChain" id="{9248f8b9-2d89-4bd0-a0e0-4768da0dbd3e}">
        <relationship name="effects">
            <destination>{278ed0c0-36ab-4bdc-b581-128d69186a63}</destination>
            <destination>{b724a148-5394-4ac9-b720-93ab9a932298}</destination>
        </relationship>
    </object>
    <object class="MixerBusPanner" id="{5b5fc3e6-0aef-4f78-b465-fbec0dfb90ba}"/>
    <object class="MixerBusFader" id="{1068a2bf-0aac-4543-9703-fb0af130f905}"/>
    <object class="FadeCurve" id="{3bb87964-4343-4950-95f3-31ccfe251980}">
        <relationship name="startPoint">
            <destination>{cfe5dbdd-b8cf-4bc4-b1df-da851808862d}</destination>
        </relationship>
        <relationship name="endPoint">
            <destination>{31fe3079-e2f5-4195-87cc-e82319aebaa9}</destination>
        </relationship>
    </object>
    <object class="MixerBusEffectChain" id="{4d6e0110-4b63-4ef2-abad-6acacf5e14de}">
        <relationship name="effects">
            <destination>{793c96d8-9e5f-4e11-9f9f-98327d05bb42}</destination>
        </relationship>
    </object>
    <object class="MixerBusPanner" id="{6783ff2a-12ee-4177-846b-4cf5a04a132b}"/>
    <object class="MixerBusEffectChain" id="{3804ea53-b0d8-4269-8f5b-53eb305e14f3}">
        <relationship name="effects">
            <destination>{eda93858-a014-46da-8ae3-c76537065781}</destination>
        </relationship>
    </object>
    <object class="MixerBusPanner" id="{30ffef6e-118d-4d28-afca-94d3ecbb1d33}"/>
    <object class="FadeCurve" id="{c7ea6da9-ab3c-463b-8ac6-58139b93c1ba}">
        <relationship name="startPoint">
            <destination>{9e614e09-6e2a-47b6-bd3d-7e1e8445ba3f}</destination>
        </relationship>
        <relationship name="endPoint">
            <destination>{32721db3-29dc-4c0c-904b-e3835e751044}</destination>
        </relationship>
    </object>
    <object class="MixerBusEffectChain" id="{94faf1a6-c530-437f-83e5-f9714b7c647c}">
        <relationship name="effects">
            <destination>{f256d9e3-b098-4cd6-9ca7-6170c8c1bbc7}</destination>
        </relationship>
    </object>
    <object class="MixerBusPanner" id="{00ddd211-69ac-4dd0-aca9-935acb94e80c}"/>
    <object class="MixerBusFader" id="{278ed0c0-36ab-4bdc-b581-128d69186a63}"/>
    <object class="SpatialiserEffect" id="{b724a148-5394-4ac9-b720-93ab9a932298}"/>
    <object class="AutomationPoint" id="{cfe5dbdd-b8cf-4bc4-b1df-da851808862d}">
        <property name="position">
            <value>0</value>
        </property>
        <property name="value">
            <value>0</value>
        </property>
        <property name="curveShape">
            <value>-0.2547189</value>
        </property>
    </object>
    <object class="AutomationPoint" id="{31fe3079-e2f5-4195-87cc-e82319aebaa9}">
        <property name="position">
            <value>5.6835379323899389</value>
        </property>
        <property name="value">
            <value>1</value>
        </property>
    </object>
    <object class="MixerBusFader" id="{793c96d8-9e5f-4e11-9f9f-98327d05bb42}"/>
    <object class="MixerBusFader" id="{eda93858-a014-46da-8ae3-c76537065781}"/>
    <object class="AutomationPoint" id="{9e614e09-6e2a-47b6-bd3d-7e1e8445ba3f}">
        <property name="position">
            <value>0</value>
        </property>
        <property name="value">
            <value>0</value>
        </property>
        <property name="curveShape">
            <value>-0.2547189</value>
        </property>
    </object>
    <object class="AutomationPoint" id="{32721db3-29dc-4c0c-904b-e3835e751044}">
        <property name="position">
            <value>6</value>
        </property>
        <property name="value">
            <value>1</value>
        </property>
    </object>
    <object class="MixerBusFader" id="{f256d9e3-b098-4cd6-9ca7-6170c8c1bbc7}"/>
</objects>
